{
	"info": {
		"_postman_id": "74b0de97-e0b7-476e-9f98-89e24da7afd5",
		"name": "Chat System",
		"schema": "https://schema.getpostman.com/json/collection/v2.1.0/collection.json",
		"_exporter_id": "21226281"
	},
	"item": [
		{
			"name": "Get Applications",
			"request": {
				"method": "GET",
				"header": [],
				"url": {
					"raw": "http://localhost:3000/applications",
					"protocol": "http",
					"host": [
						"localhost"
					],
					"port": "3000",
					"path": [
						"applications"
					]
				}
			},
			"response": []
		},
		{
			"name": "Create Application",
			"request": {
				"method": "POST",
				"header": [],
				"url": {
					"raw": "http://localhost:3000/applications?application[name]=Instabug",
					"protocol": "http",
					"host": [
						"localhost"
					],
					"port": "3000",
					"path": [
						"applications"
					],
					"query": [
						{
							"key": "application[name]",
							"value": "Instabug"
						}
					]
				}
			},
			"response": []
		},
		{
			"name": "Get Chats",
			"request": {
				"method": "GET",
				"header": [],
				"url": {
					"raw": "http://localhost:3000/applications/LTREyiBCEW8JyXqBG5VECr7RtuYqoqduBZHS/chats/",
					"protocol": "http",
					"host": [
						"localhost"
					],
					"port": "3000",
					"path": [
						"applications",
						"LTREyiBCEW8JyXqBG5VECr7RtuYqoqduBZHS",
						"chats",
						""
					]
				}
			},
			"response": []
		},
		{
			"name": "Get Chat",
			"request": {
				"method": "GET",
				"header": [],
				"url": {
					"raw": "http://localhost:3000/applications/xeoSnKkvhf4Nevux5BgFmoiNR1JSCWcBJaDr/chats/1",
					"protocol": "http",
					"host": [
						"localhost"
					],
					"port": "3000",
					"path": [
						"applications",
						"xeoSnKkvhf4Nevux5BgFmoiNR1JSCWcBJaDr",
						"chats",
						"1"
					]
				}
			},
			"response": []
		},
		{
			"name": "Get Application",
			"request": {
				"method": "GET",
				"header": [],
				"url": {
					"raw": "http://localhost:3000/applications/xeoSnKkvhf4Nevux5BgFmoiNR1JSCWcBJaDr",
					"protocol": "http",
					"host": [
						"localhost"
					],
					"port": "3000",
					"path": [
						"applications",
						"xeoSnKkvhf4Nevux5BgFmoiNR1JSCWcBJaDr"
					]
				}
			},
			"response": []
		},
		{
			"name": "Get Messages",
			"request": {
				"method": "GET",
				"header": [],
				"url": {
					"raw": "http://localhost:3000/applications/m9UL8uBm1pvmCCw9m38HiNe6ribfBMQrpV7u/chats/1/messages",
					"protocol": "http",
					"host": [
						"localhost"
					],
					"port": "3000",
					"path": [
						"applications",
						"m9UL8uBm1pvmCCw9m38HiNe6ribfBMQrpV7u",
						"chats",
						"1",
						"messages"
					]
				}
			},
			"response": []
		},
		{
			"name": "Get Message",
			"request": {
				"method": "GET",
				"header": [],
				"url": {
					"raw": "http://localhost:3000/applications/m9UL8uBm1pvmCCw9m38HiNe6ribfBMQrpV7u/chats/1/messages/12",
					"protocol": "http",
					"host": [
						"localhost"
					],
					"port": "3000",
					"path": [
						"applications",
						"m9UL8uBm1pvmCCw9m38HiNe6ribfBMQrpV7u",
						"chats",
						"1",
						"messages",
						"12"
					]
				}
			},
			"response": []
		},
		{
			"name": "Search Messages",
			"request": {
				"method": "GET",
				"header": [],
				"url": {
					"raw": "http://localhost:3000/applications/obBLZZfrqVFjn9w1TBiottLJk2q2rDBHDqW4/chats/1/search?query=odd",
					"protocol": "http",
					"host": [
						"localhost"
					],
					"port": "3000",
					"path": [
						"applications",
						"obBLZZfrqVFjn9w1TBiottLJk2q2rDBHDqW4",
						"chats",
						"1",
						"search"
					],
					"query": [
						{
							"key": "query",
							"value": "odd"
						}
					]
				}
			},
			"response": []
		},
		{
			"name": "Create Chat",
			"request": {
				"method": "POST",
				"header": [],
				"url": {
					"raw": "http://localhost:3000/applications/LTREyiBCEW8JyXqBG5VECr7RtuYqoqduBZHS/chats/",
					"protocol": "http",
					"host": [
						"localhost"
					],
					"port": "3000",
					"path": [
						"applications",
						"LTREyiBCEW8JyXqBG5VECr7RtuYqoqduBZHS",
						"chats",
						""
					]
				}
			},
			"response": []
		},
		{
			"name": "Create Message",
			"request": {
				"method": "POST",
				"header": [],
				"url": {
					"raw": "http://localhost:3000/applications/m9UL8uBm1pvmCCw9m38HiNe6ribfBMQrpV7u/chats/1/messages?message[body]=creating a new message",
					"protocol": "http",
					"host": [
						"localhost"
					],
					"port": "3000",
					"path": [
						"applications",
						"m9UL8uBm1pvmCCw9m38HiNe6ribfBMQrpV7u",
						"chats",
						"1",
						"messages"
					],
					"query": [
						{
							"key": "message[body]",
							"value": "creating a new message"
						}
					]
				}
			},
			"response": []
		},
		{
			"name": "Edit Message",
			"request": {
				"method": "PUT",
				"header": [],
				"url": {
					"raw": "http://localhost:3000/applications/xeoSnKkvhf4Nevux5BgFmoiNR1JSCWcBJaDr/chats/1/messages/1?message[body]=new message",
					"protocol": "http",
					"host": [
						"localhost"
					],
					"port": "3000",
					"path": [
						"applications",
						"xeoSnKkvhf4Nevux5BgFmoiNR1JSCWcBJaDr",
						"chats",
						"1",
						"messages",
						"1"
					],
					"query": [
						{
							"key": "message[body]",
							"value": "new message"
						}
					]
				}
			},
			"response": []
		},
		{
			"name": "Edit Application",
			"request": {
				"method": "PUT",
				"header": [],
				"url": {
					"raw": "http://localhost:3000/applications/xeoSnKkvhf4Nevux5BgFmoiNR1JSCWcBJaDr/?application[name]=Instabug v2.0",
					"protocol": "http",
					"host": [
						"localhost"
					],
					"port": "3000",
					"path": [
						"applications",
						"xeoSnKkvhf4Nevux5BgFmoiNR1JSCWcBJaDr",
						""
					],
					"query": [
						{
							"key": "application[name]",
							"value": "Instabug v2.0"
						}
					]
				}
			},
			"response": []
		}
	]
}